{
  "main": {
    "id": "52affe4dffc0fc21",
    "type": "split",
    "children": [
      {
        "id": "3616ffab2ac28829",
        "type": "tabs",
        "children": [
          {
            "id": "94fd80d48bd52aed",
            "type": "leaf",
            "state": {
              "type": "markdown",
              "state": {
                "file": "ASTRO2/ASTRO2 08-23-23 Lecture 1.md",
                "mode": "source",
                "source": false
              }
            }
          }
        ]
      }
    ],
    "direction": "vertical"
  },
  "left": {
    "id": "a23a55fe1af4b785",
    "type": "split",
    "children": [
      {
        "id": "ba5b88461361e88e",
        "type": "tabs",
        "children": [
          {
            "id": "8e0867072911751c",
            "type": "leaf",
            "state": {
              "type": "file-explorer",
              "state": {
                "sortOrder": "alphabetical"
              }
            }
          },
          {
            "id": "ca951ab004313d3d",
            "type": "leaf",
            "state": {
              "type": "search",
              "state": {
                "query": "",
                "matchingCase": false,
                "explainSearch": false,
                "collapseAll": false,
                "extraContext": false,
                "sortOrder": "alphabetical"
              }
            }
          },
          {
            "id": "465bb873b2bc962a",
            "type": "leaf",
            "state": {
              "type": "bookmarks",
              "state": {}
            }
          }
        ]
      }
    ],
    "direction": "horizontal",
    "width": 300
  },
  "right": {
    "id": "3afcbafc664a87b1",
    "type": "split",
    "children": [
      {
        "id": "e4df6c81de2cfd9d",
        "type": "tabs",
        "children": [
          {
            "id": "59518c762ceca2c8",
            "type": "leaf",
            "state": {
              "type": "backlink",
              "state": {
                "file": "ASTRO2/ASTRO2 08-23-23 Lecture 1.md",
                "collapseAll": false,
                "extraContext": false,
                "sortOrder": "alphabetical",
                "showSearch": false,
                "searchQuery": "",
                "backlinkCollapsed": false,
                "unlinkedCollapsed": true
              }
            }
          },
          {
            "id": "491d2c7b487883a4",
            "type": "leaf",
            "state": {
              "type": "outgoing-link",
              "state": {
                "file": "ASTRO2/ASTRO2 08-23-23 Lecture 1.md",
                "linksCollapsed": false,
                "unlinkedCollapsed": true
              }
            }
          },
          {
            "id": "a8b845b08d6e6236",
            "type": "leaf",
            "state": {
              "type": "tag",
              "state": {
                "sortOrder": "frequency",
                "useHierarchy": true
              }
            }
          },
          {
            "id": "05810173da54a740",
            "type": "leaf",
            "state": {
              "type": "outline",
              "state": {
                "file": "ASTRO2/ASTRO2 08-23-23 Lecture 1.md"
              }
            }
          }
        ]
      }
    ],
    "direction": "horizontal",
    "width": 300,
    "collapsed": true
  },
  "left-ribbon": {
    "hiddenItems": {
      "switcher:Open quick switcher": false,
      "graph:Open graph view": false,
      "canvas:Create new canvas": false,
      "daily-notes:Open today's daily note": false,
      "templates:Insert template": false,
      "command-palette:Open command palette": false
    }
  },
  "active": "8e0867072911751c",
  "lastOpenFiles": [
    "NEWT/NEWT 08-23-23 Lecture 1.md",
    "ML/ML 08-24-23 Lecture 1.md",
    "ASTRO2/ASTRO2 08-23-23 Lecture 1.md",
    "ALGO/ALGO 08-24-23 Lecture 1.md",
    "DAILY/2023-08-24.md",
    "ML",
    "ALGO",
    "OS/OS 8-24-23 Lecture 1.md",
    "DAILY/2023-08-23.md",
    "DAILY/2023-07-09.md",
    "ASTRO2",
    "NEWT"
  ]
}